{
  "statusCode": 200,
  "statusText": "Ok",
  "data": {
    "testId": "160512_SH_KWX",
    "ownerKey": "660010c19934e23af63f8078cb142ea64749734f",
    "jsonUrl": "http://www.webpagetest.org/jsonResult.php?test=160512_SH_KWX",
    "xmlUrl": "http://www.webpagetest.org/xmlResult/160512_SH_KWX/",
    "userUrl": "http://www.webpagetest.org/result/160512_SH_KWX/",
    "summaryCSV": "http://www.webpagetest.org/result/160512_SH_KWX/page_data.csv",
    "detailCSV": "http://www.webpagetest.org/result/160512_SH_KWX/requests.csv"
  }
}